<?xml version="1.0" encoding="UTF-8"?>
<SceneScript lower="0" upper="0">
  <SceneObject lower="0" upper="113" language="@@" identifier="InformStartData">
    <SceneTurn lower="25" upper="113" speaker="web">
      <SceneUttr lower="31" upper="113" punct=".">
        <ActionObject lower="31" upper="38" actor="" name="PROCEED">
          <ActionFeature lower="39" upper="111" key="value" val="'Once ready, click button to collect some data about participant.'"/>
        </ActionObject>
      </SceneUttr>
    </SceneTurn>
  </SceneObject>
  <SceneObject lower="115" upper="202" language="@@" identifier="InformParticipantInfoFill">
    <SceneTurn lower="150" upper="202" speaker="web">
      <SceneUttr lower="156" upper="202" punct=".">
        <ActionObject lower="156" upper="162" actor="" name="INFORM">
          <ActionFeature lower="163" upper="200" key="value" val="'Fill participant information.'"/>
        </ActionObject>
      </SceneUttr>
    </SceneTurn>
  </SceneObject>
  <SceneObject lower="204" upper="311" language="@@" identifier="RequestParticipantInfo">
    <SceneTurn lower="236" upper="311" speaker="web">
      <SceneUttr lower="242" upper="311" punct=".">
        <ActionObject lower="242" upper="249" actor="" name="REQUEST">
          <ActionFeature lower="250" upper="260" key="var" val="'name'"/>
          <ActionFeature lower="261" upper="297" key="value" val="'Enter participants pseudonym'"/>
          <ActionFeature lower="298" upper="309" key="type" val="'text'"/>
        </ActionObject>
      </SceneUttr>
    </SceneTurn>
  </SceneObject>
  <SceneObject lower="313" upper="401" language="@@" identifier="InformStartExp">
    <SceneTurn lower="337" upper="401" speaker="web">
      <SceneUttr lower="343" upper="401" punct=".">
        <ActionObject lower="343" upper="350" actor="" name="PROCEED">
          <ActionFeature lower="351" upper="399" key="value" val="'Start experiment by clicking the button.'"/>
        </ActionObject>
      </SceneUttr>
    </SceneTurn>
  </SceneObject>
  <SceneObject lower="403" upper="465" language="@@" identifier="InformPhase1">
    <SceneTurn lower="425" upper="465" speaker="web">
      <SceneUttr lower="431" upper="465" punct=".">
        <ActionObject lower="431" upper="437" actor="" name="INFORM">
          <ActionFeature lower="438" upper="463" key="value" val="'Phase 1: Greeting'"/>
        </ActionObject>
      </SceneUttr>
    </SceneTurn>
  </SceneObject>
  <SceneObject lower="467" upper="530" language="@@" identifier="InformPhase2">
    <SceneTurn lower="489" upper="530" speaker="web">
      <SceneUttr lower="495" upper="530" punct=".">
        <ActionObject lower="495" upper="501" actor="" name="INFORM">
          <ActionFeature lower="502" upper="528" key="value" val="'Phase 2: Adressing'"/>
        </ActionObject>
      </SceneUttr>
    </SceneTurn>
  </SceneObject>
  <SceneObject lower="532" upper="595" language="@@" identifier="InformPhase3">
    <SceneTurn lower="554" upper="595" speaker="web">
      <SceneUttr lower="560" upper="595" punct=".">
        <ActionObject lower="560" upper="566" actor="" name="INFORM">
          <ActionFeature lower="567" upper="593" key="value" val="'Phase 3: Including'"/>
        </ActionObject>
      </SceneUttr>
    </SceneTurn>
  </SceneObject>
    <SceneObject lower="597" upper="658" language="@@" identifier="InformPhase4">
        <SceneTurn lower="619" upper="658" speaker="web">
            <SceneUttr lower="625" upper="658" punct=".">
                <ActionObject lower="625" upper="631" actor="" name="INFORM">
                    <ActionFeature lower="632" upper="656" key="value" val="'Phase 4: Solving'"/>
                </ActionObject>
            </SceneUttr>
        </SceneTurn>
    </SceneObject>
    <SceneObject lower="660" upper="892" language="@@" identifier="RequestConflictInterpretation">
        <SceneTurn lower="699" upper="892" speaker="web">
            <SceneUttr lower="705" upper="892" punct=".">
                <ActionObject lower="705" upper="712" actor="" name="REQUEST">
                    <ActionFeature lower="713" upper="796" key="var"
                                   val="'affection_interpretation;freedom_interpretation;task_interpretation;phase_tmp'"/>
                    <ActionFeature lower="797" upper="859" key="value"
                                   val="'Yes,No,Undecided;Yes,No,Undecided;Good,Bad;P1,P2,P3,P4'"/>
                    <ActionFeature lower="860" upper="890" key="type" val="'radio;radio;radio;radio'"/>
                </ActionObject>
            </SceneUttr>
        </SceneTurn>
    </SceneObject>
</SceneScript>